examples/__init__.py
examples/jupyter_notebook_config.py
examples/NY-restaurants/__init__.py
examples/NY-restaurants/ingest.py
examples/imdb/__init__.py
examples/imdb/load.py
examples/imdb/serialize.py
pandagg/__init__.py
pandagg/_decorators.py
pandagg/aggs.py
pandagg/discovery.py
pandagg/document.py
pandagg/exceptions.py
pandagg/index.py
pandagg/mappings.py
pandagg/query.py
pandagg/response.py
pandagg/search.py
pandagg/types.py
pandagg/utils.py
pandagg/interactive/__init__.py
pandagg/interactive/_field_agg_factory.py
pandagg/interactive/mappings.py
pandagg/node/__init__.py
pandagg/node/_node.py
pandagg/node/types.py
pandagg/node/aggs/__init__.py
pandagg/node/aggs/abstract.py
pandagg/node/aggs/bucket.py
pandagg/node/aggs/composite.py
pandagg/node/aggs/metric.py
pandagg/node/aggs/pipeline.py
pandagg/node/mappings/__init__.py
pandagg/node/mappings/abstract.py
pandagg/node/mappings/field_datatypes.py
pandagg/node/mappings/meta_fields.py
pandagg/node/query/__init__.py
pandagg/node/query/_parameter_clause.py
pandagg/node/query/abstract.py
pandagg/node/query/compound.py
pandagg/node/query/full_text.py
pandagg/node/query/geo.py
pandagg/node/query/joining.py
pandagg/node/query/match_all.py
pandagg/node/query/shape.py
pandagg/node/query/span.py
pandagg/node/query/specialized.py
pandagg/node/query/specialized_compound.py
pandagg/node/query/term_level.py
pandagg/tree/__init__.py
pandagg/tree/_tree.py
pandagg/tree/aggs.py
pandagg/tree/mappings.py
pandagg/tree/query.py
tests/__init__.py
tests/conftest.py
tests/test_data.py
tests/test_discovery.py
tests/test_document.py
tests/test_index.py
tests/test_response.py
tests/test_search.py
tests/test_utils.py
tests/interactive/__init__.py
tests/interactive/test_mapping.py
tests/node/__init__.py
tests/node/agg/__init__.py
tests/node/agg/test_abstract.py
tests/node/agg/test_bucket.py
tests/node/agg/test_metric.py
tests/node/agg/test_pipeline.py
tests/node/mapping/__init__.py
tests/node/mapping/test_field.py
tests/node/query/__init__.py
pandagg-0.2.4.dist-info/AUTHORS
pandagg-0.2.4.dist-info/LICENSE
pandagg-0.2.4.dist-info/METADATA
pandagg-0.2.4.dist-info/WHEEL
pandagg-0.2.4.dist-info/top_level.txt
pandagg-0.2.4.dist-info/RECORD
