Metadata-Version: 2.1
Name: pandagg
Version: 0.2.4
Summary: Python package provided to make elasticsearch aggregations and queries easy.
Home-page: https://github.com/alkemics/pandagg
Author: Léonard Binet
Author-email: leonardbinet@gmail.com
License: Apache-2.0
Keywords: elasticsearch aggregation pandas
Platform: UNKNOWN
License-File: LICENSE
License-File: AUTHORS
Requires-Dist: lighttree (==1.3.4)
Requires-Dist: elasticsearch (<8.0.0,>=7.0.0)
Requires-Dist: typing-extensions
Provides-Extra: develop
Requires-Dist: pre-commit ; extra == 'develop'
Requires-Dist: black ; extra == 'develop'
Requires-Dist: coverage ; extra == 'develop'
Requires-Dist: flake8 ; extra == 'develop'
Requires-Dist: pytest ; extra == 'develop'
Requires-Dist: pytest-cov ; extra == 'develop'
Requires-Dist: mock ; extra == 'develop'
Requires-Dist: mypy ; extra == 'develop'
Requires-Dist: pandas ; extra == 'develop'
Requires-Dist: Sphinx ; extra == 'develop'
Requires-Dist: twine ; extra == 'develop'
